ciridrive_python/__init__.py
ciridrive_python/main_ciridrive.py
ciridrive_python-1.6.dist-info/LICENSE
ciridrive_python-1.6.dist-info/METADATA
ciridrive_python-1.6.dist-info/WHEEL
ciridrive_python-1.6.dist-info/top_level.txt
ciridrive_python-1.6.dist-info/RECORD
