Metadata-Version: 2.1
Name: ciridrive-python
Version: 1.6
Summary: This library simplifies the integration of python algorithms with Google drive | Essa biblioteca simplifica a integração de algoritmos em python, com o Google drive
Home-page: https://github.com/Rafael-Cirino/Ciridrive
Author: Rafael Cirino
Author-email: rafael.cirino@unicamperacing.com.br
License: MIT
Platform: UNKNOWN
